README.txt
setup.cfg
setup.py
lbn/__init__.py
lbn.zenoss.egg-info/PKG-INFO
lbn.zenoss.egg-info/SOURCES.txt
lbn.zenoss.egg-info/dependency_links.txt
lbn.zenoss.egg-info/entry_points.txt
lbn.zenoss.egg-info/namespace_packages.txt
lbn.zenoss.egg-info/not-zip-safe
lbn.zenoss.egg-info/requires.txt
lbn.zenoss.egg-info/top_level.txt
lbn/zenoss/__init__.py
lbn/zenoss/base.py
lbn/zenoss/configure.zcml
lbn/zenoss/monkeypatches.py
lbn/zenoss/packutils.py
lbn/zenoss/browser/__init__.py
lbn/zenoss/browser/configure.zcml
lbn/zenoss/browser/zenfixers.py
lbn/zenoss/browser/zensetup.py
lbn/zenoss/dtml/properties.dtml
lbn/zenoss/www/RelationshipManager_icon.gif
lbn/zenoss/www/ZenossInfo_icon.gif
lbn/zenoss/www/portletmanager.gif