Metadata-Version: 1.0
Name: lbn.zenoss
Version: 3.0.4
Summary: Base wrappers to save real Zopistas from Zenoss cruft
Home-page: http://au.last-bastion.net/zenoss
Author: Alan Milligan
Author-email: alan.milligan@last-bastion.net
License: ZPL/2.1
Keywords: lbn zenoss
Platform: UNKNOWN
Classifier: Framework :: Zope2
Classifier: Framework :: Plone
Classifier: Intended Audience :: Information Technology
Classifier: Programming Language :: Python
Classifier: Programming Language :: Zope
Classifier: Development Status :: 5 - Production/Stable
Classifier: License :: OSI Approved :: Zope Public License
Classifier: Topic :: System :: Monitoring
Classifier: Topic :: System :: Networking :: Monitoring
